[
    {
        "game": "3D Starstrike",
        "link": "https://www.mobygames.com/game/30029/3d-starstrike/",
        "game_code": "3d-starstrike"
    },
    {
        "game": "Adventure Quest",
        "link": "https://www.mobygames.com/game/26902/adventure-quest/",
        "game_code": "adventure-quest"
    },
    {
        "game": "Airwolf",
        "link": "https://www.mobygames.com/game/220910/airwolf/",
        "game_code": "airwolf"
    },
    {
        "game": "Animal Vegetable Mineral",
        "link": "https://www.mobygames.com/game/50860/animal-vegetable-mineral/",
        "game_code": "animal-vegetable-mineral"
    },
    {
        "game": "Attack of the Petscii Robots",
        "link": "https://www.mobygames.com/game/157357/attack-of-the-petscii-robots/",
        "game_code": "attack-of-the-petscii-robots"
    },
    {
        "game": "Beach-Head",
        "link": "https://www.mobygames.com/game/19932/beach-head/",
        "game_code": "beach-head"
    },
    {
        "game": "Colossal Adventure",
        "link": "https://www.mobygames.com/game/26732/colossal-adventure/",
        "game_code": "colossal-adventure"
    },
    {
        "game": "Cyrus II Chess",
        "link": "https://www.mobygames.com/game/57916/cyrus-ii-chess/",
        "game_code": "cyrus-ii-chess"
    },
    {
        "game": "Dictator",
        "link": "https://www.mobygames.com/game/18637/dictator/",
        "game_code": "dictator"
    },
    {
        "game": "Dungeon Adventure",
        "link": "https://www.mobygames.com/game/26903/dungeon-adventure/",
        "game_code": "dungeon-adventure"
    },
    {
        "game": "Emerald Isle",
        "link": "https://www.mobygames.com/game/56324/emerald-isle/",
        "game_code": "emerald-isle"
    },
    {
        "game": "Fantasia Diamond",
        "link": "https://www.mobygames.com/game/80826/fantasia-diamond/",
        "game_code": "fantasia-diamond"
    },
    {
        "game": "Finders Keepers",
        "link": "https://www.mobygames.com/game/19116/finders-keepers/",
        "game_code": "finders-keepers"
    },
    {
        "game": "Formula 1 Simulator",
        "link": "https://www.mobygames.com/game/20034/formula-1-simulator/",
        "game_code": "formula-1-simulator"
    },
    {
        "game": "Grime Z80",
        "link": "https://www.mobygames.com/game/113647/grime-z80/",
        "game_code": "grime-z80"
    },
    {
        "game": "Lords of Time",
        "link": "https://www.mobygames.com/game/28777/lords-of-time/",
        "game_code": "lords-of-time"
    },
    {
        "game": "Mordon's Quest",
        "link": "https://www.mobygames.com/game/29926/mordons-quest/",
        "game_code": "mordons-quest"
    },
    {
        "game": "Nodes of Yesod",
        "link": "https://www.mobygames.com/game/22371/nodes-of-yesod/",
        "game_code": "nodes-of-yesod"
    },
    {
        "game": "Nonterraqueous",
        "link": "https://www.mobygames.com/game/21854/nonterraqueous/",
        "game_code": "nonterraqueous"
    },
    {
        "game": "Out of This World",
        "link": "https://www.mobygames.com/game/71716/out-of-this-world/",
        "game_code": "out-of-this-world"
    },
    {
        "game": "Raid over Moscow",
        "link": "https://www.mobygames.com/game/24714/raid-over-moscow/",
        "game_code": "raid-over-moscow"
    },
    {
        "game": "Return to Eden",
        "link": "https://www.mobygames.com/game/23369/return-to-eden/",
        "game_code": "return-to-eden"
    },
    {
        "game": "Snowball",
        "link": "https://www.mobygames.com/game/23363/snowball/",
        "game_code": "snowball"
    },
    {
        "game": "Steve Davis Snooker",
        "link": "https://www.mobygames.com/game/15362/steve-davis-snooker/",
        "game_code": "steve-davis-snooker"
    },
    {
        "game": "The Lands of Havoc",
        "link": "https://www.mobygames.com/game/57011/the-lands-of-havoc/",
        "game_code": "the-lands-of-havoc"
    },
    {
        "game": "Type-Rope",
        "link": "https://www.mobygames.com/game/34346/type-rope/",
        "game_code": "type-rope"
    },
    {
        "game": "Williamsburg: Adventure 3",
        "link": "https://www.mobygames.com/game/67083/williamsburg-adventure-3/",
        "game_code": "williamsburg-adventure-3"
    },
    {
        "game": "Wizard's Lair",
        "link": "https://www.mobygames.com/game/14938/wizards-lair/",
        "game_code": "wizards-lair"
    },
    {
        "game": "Wriggler",
        "link": "https://www.mobygames.com/game/17216/wriggler/",
        "game_code": "wriggler"
    }
]